onleiharr/__init__.py
onleiharr/__main__.py
onleiharr/_version.py
onleiharr/cli.py
onleiharr/config.py
onleiharr/models.py
onleiharr/onleihe.py
onleiharr/parser.py
onleiharr-0.1.0.dist-info/licenses/LICENSE
onleiharr-0.1.0.dist-info/METADATA
onleiharr-0.1.0.dist-info/WHEEL
onleiharr-0.1.0.dist-info/entry_points.txt
onleiharr-0.1.0.dist-info/top_level.txt
onleiharr-0.1.0.dist-info/RECORD
