Metadata-Version: 2.4
Name: onleiharr
Version: 0.1.0
Summary: Onleihe watcher with notifications and auto-rent
Author: Onleiharr Maintainers
License-Expression: MIT
Project-URL: Homepage, https://github.com/nzb-tuxxx/Onleiharr
Project-URL: Repository, https://github.com/nzb-tuxxx/Onleiharr
Project-URL: Issues, https://github.com/nzb-tuxxx/Onleiharr/issues
Keywords: onleiharr,onleihe
Classifier: Programming Language :: Python :: 3
Classifier: Programming Language :: Python :: 3 :: Only
Classifier: Intended Audience :: End Users/Desktop
Classifier: Environment :: Console
Requires-Python: >=3.10
License-File: LICENSE
Requires-Dist: apprise
Requires-Dist: beautifulsoup4
Requires-Dist: requests
Requires-Dist: tomli; python_version < "3.11"
Dynamic: license-file
